Metadata-Version: 1.1
Name: pattmatch
Version: 0.0.2
Summary: Implementation of some pattern matching algorithms
Home-page: https://github.com/monzita/pattmatch
Author: Monika Ilieva
Author-email: hidden@hidden.com
License: GNU General Public License v3 or later (GPLv3+)
Keywords: pattern-matching text string pattern python3 boyer moore rabin karp kmp
Platform: UNKNOWN
Classifier: Development Status :: 3 - Alpha
Classifier: Intended Audience :: Developers
Classifier: Topic :: Software Development :: Build Tools
Classifier: Programming Language :: Python :: 3.6
